{
  "problem": "IMO 2025 Problem 6: Tile Placement",
  "description": "Minimize tiles on n\u00d7n grid such that each row and column has exactly 1 uncovered square",
  "theoretical_analysis": {
    "2": {
      "grid_size": 4,
      "uncovered_count": 2,
      "covered_count": 2,
      "theoretical_lower_bound": 1,
      "diagonal_strategy_bound": 2,
      "formula": "For diagonal pattern: 2n - 2 tiles",
      "imo_2025_answer": 4048
    },
    "3": {
      "grid_size": 9,
      "uncovered_count": 3,
      "covered_count": 6,
      "theoretical_lower_bound": 1,
      "diagonal_strategy_bound": 4,
      "formula": "For diagonal pattern: 2n - 2 tiles",
      "imo_2025_answer": 4048
    },
    "5": {
      "grid_size": 25,
      "uncovered_count": 5,
      "covered_count": 20,
      "theoretical_lower_bound": 1,
      "diagonal_strategy_bound": 8,
      "formula": "For diagonal pattern: 2n - 2 tiles",
      "imo_2025_answer": 4048
    },
    "10": {
      "grid_size": 100,
      "uncovered_count": 10,
      "covered_count": 90,
      "theoretical_lower_bound": 1,
      "diagonal_strategy_bound": 18,
      "formula": "For diagonal pattern: 2n - 2 tiles",
      "imo_2025_answer": 4048
    },
    "100": {
      "grid_size": 10000,
      "uncovered_count": 100,
      "covered_count": 9900,
      "theoretical_lower_bound": 1,
      "diagonal_strategy_bound": 198,
      "formula": "For diagonal pattern: 2n - 2 tiles",
      "imo_2025_answer": 4048
    },
    "2025": {
      "grid_size": 4100625,
      "uncovered_count": 2025,
      "covered_count": 4098600,
      "theoretical_lower_bound": 1,
      "diagonal_strategy_bound": 4048,
      "formula": "For diagonal pattern: 2n - 2 tiles",
      "imo_2025_answer": 4048
    }
  },
  "small_cases": {
    "2": {
      "n": 2,
      "minimum_tiles": 2,
      "best_strategy": "diagonal_horizontal",
      "tiles": [
        [
          0,
          1,
          1,
          1
        ],
        [
          1,
          0,
          1,
          1
        ]
      ],
      "all_strategies": {
        "diagonal_horizontal": {
          "count": 2,
          "tiles": [
            [
              0,
              1,
              1,
              1
            ],
            [
              1,
              0,
              1,
              1
            ]
          ]
        },
        "anti_diagonal_horizontal": {
          "count": 2,
          "tiles": [
            [
              0,
              0,
              1,
              1
            ],
            [
              1,
              1,
              1,
              1
            ]
          ]
        },
        "optimized_vertical": {
          "count": 2,
          "tiles": [
            [
              1,
              0,
              1,
              1
            ],
            [
              0,
              1,
              1,
              1
            ]
          ]
        },
        "single_large_attempt": {
          "count": 2,
          "tiles": [
            [
              1,
              0,
              1,
              1
            ],
            [
              0,
              1,
              1,
              1
            ]
          ]
        }
      },
      "is_valid": true,
      "uncovered_positions": [
        [
          1,
          1
        ],
        [
          0,
          0
        ]
      ]
    },
    "3": {
      "n": 3,
      "minimum_tiles": 4,
      "best_strategy": "diagonal_horizontal",
      "tiles": [
        [
          0,
          1,
          1,
          2
        ],
        [
          1,
          0,
          1,
          1
        ],
        [
          1,
          2,
          1,
          1
        ],
        [
          2,
          0,
          1,
          2
        ]
      ],
      "all_strategies": {
        "diagonal_horizontal": {
          "count": 4,
          "tiles": [
            [
              0,
              1,
              1,
              2
            ],
            [
              1,
              0,
              1,
              1
            ],
            [
              1,
              2,
              1,
              1
            ],
            [
              2,
              0,
              1,
              2
            ]
          ]
        },
        "anti_diagonal_horizontal": {
          "count": 4,
          "tiles": [
            [
              0,
              0,
              1,
              2
            ],
            [
              1,
              0,
              1,
              1
            ],
            [
              1,
              2,
              1,
              1
            ],
            [
              2,
              1,
              1,
              2
            ]
          ]
        },
        "optimized_vertical": {
          "count": 4,
          "tiles": [
            [
              1,
              0,
              2,
              1
            ],
            [
              0,
              1,
              1,
              1
            ],
            [
              2,
              1,
              1,
              1
            ],
            [
              0,
              2,
              2,
              1
            ]
          ]
        },
        "single_large_attempt": {
          "count": 4,
          "tiles": [
            [
              1,
              0,
              2,
              1
            ],
            [
              0,
              1,
              1,
              1
            ],
            [
              2,
              1,
              1,
              1
            ],
            [
              0,
              2,
              2,
              1
            ]
          ]
        }
      },
      "is_valid": true,
      "uncovered_positions": [
        [
          1,
          1
        ],
        [
          2,
          2
        ],
        [
          0,
          0
        ]
      ]
    },
    "4": {
      "n": 4,
      "minimum_tiles": 6,
      "best_strategy": "diagonal_horizontal",
      "tiles": [
        [
          0,
          1,
          1,
          3
        ],
        [
          1,
          0,
          1,
          1
        ],
        [
          1,
          2,
          1,
          2
        ],
        [
          2,
          0,
          1,
          2
        ],
        [
          2,
          3,
          1,
          1
        ],
        [
          3,
          0,
          1,
          3
        ]
      ],
      "all_strategies": {
        "diagonal_horizontal": {
          "count": 6,
          "tiles": [
            [
              0,
              1,
              1,
              3
            ],
            [
              1,
              0,
              1,
              1
            ],
            [
              1,
              2,
              1,
              2
            ],
            [
              2,
              0,
              1,
              2
            ],
            [
              2,
              3,
              1,
              1
            ],
            [
              3,
              0,
              1,
              3
            ]
          ]
        },
        "anti_diagonal_horizontal": {
          "count": 6,
          "tiles": [
            [
              0,
              0,
              1,
              3
            ],
            [
              1,
              0,
              1,
              2
            ],
            [
              1,
              3,
              1,
              1
            ],
            [
              2,
              0,
              1,
              1
            ],
            [
              2,
              2,
              1,
              2
            ],
            [
              3,
              1,
              1,
              3
            ]
          ]
        },
        "optimized_vertical": {
          "count": 6,
          "tiles": [
            [
              1,
              0,
              3,
              1
            ],
            [
              0,
              1,
              1,
              1
            ],
            [
              2,
              1,
              2,
              1
            ],
            [
              0,
              2,
              2,
              1
            ],
            [
              3,
              2,
              1,
              1
            ],
            [
              0,
              3,
              3,
              1
            ]
          ]
        },
        "single_large_attempt": {
          "count": 6,
          "tiles": [
            [
              1,
              0,
              3,
              1
            ],
            [
              0,
              1,
              1,
              1
            ],
            [
              2,
              1,
              2,
              1
            ],
            [
              0,
              2,
              2,
              1
            ],
            [
              3,
              2,
              1,
              1
            ],
            [
              0,
              3,
              3,
              1
            ]
          ]
        }
      },
      "is_valid": true,
      "uncovered_positions": [
        [
          1,
          1
        ],
        [
          3,
          3
        ],
        [
          2,
          2
        ],
        [
          0,
          0
        ]
      ]
    },
    "5": {
      "n": 5,
      "minimum_tiles": 8,
      "best_strategy": "diagonal_horizontal",
      "tiles": [
        [
          0,
          1,
          1,
          4
        ],
        [
          1,
          0,
          1,
          1
        ],
        [
          1,
          2,
          1,
          3
        ],
        [
          2,
          0,
          1,
          2
        ],
        [
          2,
          3,
          1,
          2
        ],
        [
          3,
          0,
          1,
          3
        ],
        [
          3,
          4,
          1,
          1
        ],
        [
          4,
          0,
          1,
          4
        ]
      ],
      "all_strategies": {
        "diagonal_horizontal": {
          "count": 8,
          "tiles": [
            [
              0,
              1,
              1,
              4
            ],
            [
              1,
              0,
              1,
              1
            ],
            [
              1,
              2,
              1,
              3
            ],
            [
              2,
              0,
              1,
              2
            ],
            [
              2,
              3,
              1,
              2
            ],
            [
              3,
              0,
              1,
              3
            ],
            [
              3,
              4,
              1,
              1
            ],
            [
              4,
              0,
              1,
              4
            ]
          ]
        },
        "anti_diagonal_horizontal": {
          "count": 8,
          "tiles": [
            [
              0,
              0,
              1,
              4
            ],
            [
              1,
              0,
              1,
              3
            ],
            [
              1,
              4,
              1,
              1
            ],
            [
              2,
              0,
              1,
              2
            ],
            [
              2,
              3,
              1,
              2
            ],
            [
              3,
              0,
              1,
              1
            ],
            [
              3,
              2,
              1,
              3
            ],
            [
              4,
              1,
              1,
              4
            ]
          ]
        },
        "optimized_vertical": {
          "count": 8,
          "tiles": [
            [
              1,
              0,
              4,
              1
            ],
            [
              0,
              1,
              1,
              1
            ],
            [
              2,
              1,
              3,
              1
            ],
            [
              0,
              2,
              2,
              1
            ],
            [
              3,
              2,
              2,
              1
            ],
            [
              0,
              3,
              3,
              1
            ],
            [
              4,
              3,
              1,
              1
            ],
            [
              0,
              4,
              4,
              1
            ]
          ]
        },
        "single_large_attempt": {
          "count": 8,
          "tiles": [
            [
              1,
              0,
              4,
              1
            ],
            [
              0,
              1,
              1,
              1
            ],
            [
              2,
              1,
              3,
              1
            ],
            [
              0,
              2,
              2,
              1
            ],
            [
              3,
              2,
              2,
              1
            ],
            [
              0,
              3,
              3,
              1
            ],
            [
              4,
              3,
              1,
              1
            ],
            [
              0,
              4,
              4,
              1
            ]
          ]
        }
      },
      "is_valid": true,
      "uncovered_positions": [
        [
          4,
          4
        ],
        [
          0,
          0
        ],
        [
          1,
          1
        ],
        [
          3,
          3
        ],
        [
          2,
          2
        ]
      ]
    },
    "6": {
      "n": 6,
      "minimum_tiles": 10,
      "best_strategy": "diagonal_horizontal",
      "tiles": [
        [
          0,
          1,
          1,
          5
        ],
        [
          1,
          0,
          1,
          1
        ],
        [
          1,
          2,
          1,
          4
        ],
        [
          2,
          0,
          1,
          2
        ],
        [
          2,
          3,
          1,
          3
        ],
        [
          3,
          0,
          1,
          3
        ],
        [
          3,
          4,
          1,
          2
        ],
        [
          4,
          0,
          1,
          4
        ],
        [
          4,
          5,
          1,
          1
        ],
        [
          5,
          0,
          1,
          5
        ]
      ],
      "all_strategies": {
        "diagonal_horizontal": {
          "count": 10,
          "tiles": [
            [
              0,
              1,
              1,
              5
            ],
            [
              1,
              0,
              1,
              1
            ],
            [
              1,
              2,
              1,
              4
            ],
            [
              2,
              0,
              1,
              2
            ],
            [
              2,
              3,
              1,
              3
            ],
            [
              3,
              0,
              1,
              3
            ],
            [
              3,
              4,
              1,
              2
            ],
            [
              4,
              0,
              1,
              4
            ],
            [
              4,
              5,
              1,
              1
            ],
            [
              5,
              0,
              1,
              5
            ]
          ]
        },
        "anti_diagonal_horizontal": {
          "count": 10,
          "tiles": [
            [
              0,
              0,
              1,
              5
            ],
            [
              1,
              0,
              1,
              4
            ],
            [
              1,
              5,
              1,
              1
            ],
            [
              2,
              0,
              1,
              3
            ],
            [
              2,
              4,
              1,
              2
            ],
            [
              3,
              0,
              1,
              2
            ],
            [
              3,
              3,
              1,
              3
            ],
            [
              4,
              0,
              1,
              1
            ],
            [
              4,
              2,
              1,
              4
            ],
            [
              5,
              1,
              1,
              5
            ]
          ]
        },
        "optimized_vertical": {
          "count": 10,
          "tiles": [
            [
              1,
              0,
              5,
              1
            ],
            [
              0,
              1,
              1,
              1
            ],
            [
              2,
              1,
              4,
              1
            ],
            [
              0,
              2,
              2,
              1
            ],
            [
              3,
              2,
              3,
              1
            ],
            [
              0,
              3,
              3,
              1
            ],
            [
              4,
              3,
              2,
              1
            ],
            [
              0,
              4,
              4,
              1
            ],
            [
              5,
              4,
              1,
              1
            ],
            [
              0,
              5,
              5,
              1
            ]
          ]
        },
        "single_large_attempt": {
          "count": 10,
          "tiles": [
            [
              1,
              0,
              5,
              1
            ],
            [
              0,
              1,
              1,
              1
            ],
            [
              2,
              1,
              4,
              1
            ],
            [
              0,
              2,
              2,
              1
            ],
            [
              3,
              2,
              3,
              1
            ],
            [
              0,
              3,
              3,
              1
            ],
            [
              4,
              3,
              2,
              1
            ],
            [
              0,
              4,
              4,
              1
            ],
            [
              5,
              4,
              1,
              1
            ],
            [
              0,
              5,
              5,
              1
            ]
          ]
        }
      },
      "is_valid": true,
      "uncovered_positions": [
        [
          4,
          4
        ],
        [
          5,
          5
        ],
        [
          0,
          0
        ],
        [
          1,
          1
        ],
        [
          3,
          3
        ],
        [
          2,
          2
        ]
      ]
    },
    "7": {
      "n": 7,
      "minimum_tiles": 12,
      "best_strategy": "diagonal_horizontal",
      "tiles": [
        [
          0,
          1,
          1,
          6
        ],
        [
          1,
          0,
          1,
          1
        ],
        [
          1,
          2,
          1,
          5
        ],
        [
          2,
          0,
          1,
          2
        ],
        [
          2,
          3,
          1,
          4
        ],
        [
          3,
          0,
          1,
          3
        ],
        [
          3,
          4,
          1,
          3
        ],
        [
          4,
          0,
          1,
          4
        ],
        [
          4,
          5,
          1,
          2
        ],
        [
          5,
          0,
          1,
          5
        ],
        [
          5,
          6,
          1,
          1
        ],
        [
          6,
          0,
          1,
          6
        ]
      ],
      "all_strategies": {
        "diagonal_horizontal": {
          "count": 12,
          "tiles": [
            [
              0,
              1,
              1,
              6
            ],
            [
              1,
              0,
              1,
              1
            ],
            [
              1,
              2,
              1,
              5
            ],
            [
              2,
              0,
              1,
              2
            ],
            [
              2,
              3,
              1,
              4
            ],
            [
              3,
              0,
              1,
              3
            ],
            [
              3,
              4,
              1,
              3
            ],
            [
              4,
              0,
              1,
              4
            ],
            [
              4,
              5,
              1,
              2
            ],
            [
              5,
              0,
              1,
              5
            ],
            [
              5,
              6,
              1,
              1
            ],
            [
              6,
              0,
              1,
              6
            ]
          ]
        },
        "anti_diagonal_horizontal": {
          "count": 12,
          "tiles": [
            [
              0,
              0,
              1,
              6
            ],
            [
              1,
              0,
              1,
              5
            ],
            [
              1,
              6,
              1,
              1
            ],
            [
              2,
              0,
              1,
              4
            ],
            [
              2,
              5,
              1,
              2
            ],
            [
              3,
              0,
              1,
              3
            ],
            [
              3,
              4,
              1,
              3
            ],
            [
              4,
              0,
              1,
              2
            ],
            [
              4,
              3,
              1,
              4
            ],
            [
              5,
              0,
              1,
              1
            ],
            [
              5,
              2,
              1,
              5
            ],
            [
              6,
              1,
              1,
              6
            ]
          ]
        },
        "optimized_vertical": {
          "count": 12,
          "tiles": [
            [
              1,
              0,
              6,
              1
            ],
            [
              0,
              1,
              1,
              1
            ],
            [
              2,
              1,
              5,
              1
            ],
            [
              0,
              2,
              2,
              1
            ],
            [
              3,
              2,
              4,
              1
            ],
            [
              0,
              3,
              3,
              1
            ],
            [
              4,
              3,
              3,
              1
            ],
            [
              0,
              4,
              4,
              1
            ],
            [
              5,
              4,
              2,
              1
            ],
            [
              0,
              5,
              5,
              1
            ],
            [
              6,
              5,
              1,
              1
            ],
            [
              0,
              6,
              6,
              1
            ]
          ]
        },
        "single_large_attempt": {
          "count": 12,
          "tiles": [
            [
              1,
              0,
              6,
              1
            ],
            [
              0,
              1,
              1,
              1
            ],
            [
              2,
              1,
              5,
              1
            ],
            [
              0,
              2,
              2,
              1
            ],
            [
              3,
              2,
              4,
              1
            ],
            [
              0,
              3,
              3,
              1
            ],
            [
              4,
              3,
              3,
              1
            ],
            [
              0,
              4,
              4,
              1
            ],
            [
              5,
              4,
              2,
              1
            ],
            [
              0,
              5,
              5,
              1
            ],
            [
              6,
              5,
              1,
              1
            ],
            [
              0,
              6,
              6,
              1
            ]
          ]
        }
      },
      "is_valid": true,
      "uncovered_positions": [
        [
          4,
          4
        ],
        [
          5,
          5
        ],
        [
          0,
          0
        ],
        [
          1,
          1
        ],
        [
          3,
          3
        ],
        [
          2,
          2
        ],
        [
          6,
          6
        ]
      ]
    },
    "8": {
      "n": 8,
      "minimum_tiles": 14,
      "best_strategy": "diagonal_horizontal",
      "tiles": [
        [
          0,
          1,
          1,
          7
        ],
        [
          1,
          0,
          1,
          1
        ],
        [
          1,
          2,
          1,
          6
        ],
        [
          2,
          0,
          1,
          2
        ],
        [
          2,
          3,
          1,
          5
        ],
        [
          3,
          0,
          1,
          3
        ],
        [
          3,
          4,
          1,
          4
        ],
        [
          4,
          0,
          1,
          4
        ],
        [
          4,
          5,
          1,
          3
        ],
        [
          5,
          0,
          1,
          5
        ],
        [
          5,
          6,
          1,
          2
        ],
        [
          6,
          0,
          1,
          6
        ],
        [
          6,
          7,
          1,
          1
        ],
        [
          7,
          0,
          1,
          7
        ]
      ],
      "all_strategies": {
        "diagonal_horizontal": {
          "count": 14,
          "tiles": [
            [
              0,
              1,
              1,
              7
            ],
            [
              1,
              0,
              1,
              1
            ],
            [
              1,
              2,
              1,
              6
            ],
            [
              2,
              0,
              1,
              2
            ],
            [
              2,
              3,
              1,
              5
            ],
            [
              3,
              0,
              1,
              3
            ],
            [
              3,
              4,
              1,
              4
            ],
            [
              4,
              0,
              1,
              4
            ],
            [
              4,
              5,
              1,
              3
            ],
            [
              5,
              0,
              1,
              5
            ],
            [
              5,
              6,
              1,
              2
            ],
            [
              6,
              0,
              1,
              6
            ],
            [
              6,
              7,
              1,
              1
            ],
            [
              7,
              0,
              1,
              7
            ]
          ]
        },
        "anti_diagonal_horizontal": {
          "count": 14,
          "tiles": [
            [
              0,
              0,
              1,
              7
            ],
            [
              1,
              0,
              1,
              6
            ],
            [
              1,
              7,
              1,
              1
            ],
            [
              2,
              0,
              1,
              5
            ],
            [
              2,
              6,
              1,
              2
            ],
            [
              3,
              0,
              1,
              4
            ],
            [
              3,
              5,
              1,
              3
            ],
            [
              4,
              0,
              1,
              3
            ],
            [
              4,
              4,
              1,
              4
            ],
            [
              5,
              0,
              1,
              2
            ],
            [
              5,
              3,
              1,
              5
            ],
            [
              6,
              0,
              1,
              1
            ],
            [
              6,
              2,
              1,
              6
            ],
            [
              7,
              1,
              1,
              7
            ]
          ]
        },
        "optimized_vertical": {
          "count": 14,
          "tiles": [
            [
              1,
              0,
              7,
              1
            ],
            [
              0,
              1,
              1,
              1
            ],
            [
              2,
              1,
              6,
              1
            ],
            [
              0,
              2,
              2,
              1
            ],
            [
              3,
              2,
              5,
              1
            ],
            [
              0,
              3,
              3,
              1
            ],
            [
              4,
              3,
              4,
              1
            ],
            [
              0,
              4,
              4,
              1
            ],
            [
              5,
              4,
              3,
              1
            ],
            [
              0,
              5,
              5,
              1
            ],
            [
              6,
              5,
              2,
              1
            ],
            [
              0,
              6,
              6,
              1
            ],
            [
              7,
              6,
              1,
              1
            ],
            [
              0,
              7,
              7,
              1
            ]
          ]
        },
        "single_large_attempt": {
          "count": 14,
          "tiles": [
            [
              1,
              0,
              7,
              1
            ],
            [
              0,
              1,
              1,
              1
            ],
            [
              2,
              1,
              6,
              1
            ],
            [
              0,
              2,
              2,
              1
            ],
            [
              3,
              2,
              5,
              1
            ],
            [
              0,
              3,
              3,
              1
            ],
            [
              4,
              3,
              4,
              1
            ],
            [
              0,
              4,
              4,
              1
            ],
            [
              5,
              4,
              3,
              1
            ],
            [
              0,
              5,
              5,
              1
            ],
            [
              6,
              5,
              2,
              1
            ],
            [
              0,
              6,
              6,
              1
            ],
            [
              7,
              6,
              1,
              1
            ],
            [
              0,
              7,
              7,
              1
            ]
          ]
        }
      },
      "is_valid": true,
      "uncovered_positions": [
        [
          4,
          4
        ],
        [
          5,
          5
        ],
        [
          7,
          7
        ],
        [
          0,
          0
        ],
        [
          1,
          1
        ],
        [
          3,
          3
        ],
        [
          2,
          2
        ],
        [
          6,
          6
        ]
      ]
    },
    "9": {
      "n": 9,
      "minimum_tiles": 16,
      "best_strategy": "diagonal_horizontal",
      "tiles": [
        [
          0,
          1,
          1,
          8
        ],
        [
          1,
          0,
          1,
          1
        ],
        [
          1,
          2,
          1,
          7
        ],
        [
          2,
          0,
          1,
          2
        ],
        [
          2,
          3,
          1,
          6
        ],
        [
          3,
          0,
          1,
          3
        ],
        [
          3,
          4,
          1,
          5
        ],
        [
          4,
          0,
          1,
          4
        ],
        [
          4,
          5,
          1,
          4
        ],
        [
          5,
          0,
          1,
          5
        ],
        [
          5,
          6,
          1,
          3
        ],
        [
          6,
          0,
          1,
          6
        ],
        [
          6,
          7,
          1,
          2
        ],
        [
          7,
          0,
          1,
          7
        ],
        [
          7,
          8,
          1,
          1
        ],
        [
          8,
          0,
          1,
          8
        ]
      ],
      "all_strategies": {
        "diagonal_horizontal": {
          "count": 16,
          "tiles": [
            [
              0,
              1,
              1,
              8
            ],
            [
              1,
              0,
              1,
              1
            ],
            [
              1,
              2,
              1,
              7
            ],
            [
              2,
              0,
              1,
              2
            ],
            [
              2,
              3,
              1,
              6
            ],
            [
              3,
              0,
              1,
              3
            ],
            [
              3,
              4,
              1,
              5
            ],
            [
              4,
              0,
              1,
              4
            ],
            [
              4,
              5,
              1,
              4
            ],
            [
              5,
              0,
              1,
              5
            ],
            [
              5,
              6,
              1,
              3
            ],
            [
              6,
              0,
              1,
              6
            ],
            [
              6,
              7,
              1,
              2
            ],
            [
              7,
              0,
              1,
              7
            ],
            [
              7,
              8,
              1,
              1
            ],
            [
              8,
              0,
              1,
              8
            ]
          ]
        },
        "anti_diagonal_horizontal": {
          "count": 16,
          "tiles": [
            [
              0,
              0,
              1,
              8
            ],
            [
              1,
              0,
              1,
              7
            ],
            [
              1,
              8,
              1,
              1
            ],
            [
              2,
              0,
              1,
              6
            ],
            [
              2,
              7,
              1,
              2
            ],
            [
              3,
              0,
              1,
              5
            ],
            [
              3,
              6,
              1,
              3
            ],
            [
              4,
              0,
              1,
              4
            ],
            [
              4,
              5,
              1,
              4
            ],
            [
              5,
              0,
              1,
              3
            ],
            [
              5,
              4,
              1,
              5
            ],
            [
              6,
              0,
              1,
              2
            ],
            [
              6,
              3,
              1,
              6
            ],
            [
              7,
              0,
              1,
              1
            ],
            [
              7,
              2,
              1,
              7
            ],
            [
              8,
              1,
              1,
              8
            ]
          ]
        },
        "optimized_vertical": {
          "count": 16,
          "tiles": [
            [
              1,
              0,
              8,
              1
            ],
            [
              0,
              1,
              1,
              1
            ],
            [
              2,
              1,
              7,
              1
            ],
            [
              0,
              2,
              2,
              1
            ],
            [
              3,
              2,
              6,
              1
            ],
            [
              0,
              3,
              3,
              1
            ],
            [
              4,
              3,
              5,
              1
            ],
            [
              0,
              4,
              4,
              1
            ],
            [
              5,
              4,
              4,
              1
            ],
            [
              0,
              5,
              5,
              1
            ],
            [
              6,
              5,
              3,
              1
            ],
            [
              0,
              6,
              6,
              1
            ],
            [
              7,
              6,
              2,
              1
            ],
            [
              0,
              7,
              7,
              1
            ],
            [
              8,
              7,
              1,
              1
            ],
            [
              0,
              8,
              8,
              1
            ]
          ]
        },
        "single_large_attempt": {
          "count": 16,
          "tiles": [
            [
              1,
              0,
              8,
              1
            ],
            [
              0,
              1,
              1,
              1
            ],
            [
              2,
              1,
              7,
              1
            ],
            [
              0,
              2,
              2,
              1
            ],
            [
              3,
              2,
              6,
              1
            ],
            [
              0,
              3,
              3,
              1
            ],
            [
              4,
              3,
              5,
              1
            ],
            [
              0,
              4,
              4,
              1
            ],
            [
              5,
              4,
              4,
              1
            ],
            [
              0,
              5,
              5,
              1
            ],
            [
              6,
              5,
              3,
              1
            ],
            [
              0,
              6,
              6,
              1
            ],
            [
              7,
              6,
              2,
              1
            ],
            [
              0,
              7,
              7,
              1
            ],
            [
              8,
              7,
              1,
              1
            ],
            [
              0,
              8,
              8,
              1
            ]
          ]
        }
      },
      "is_valid": true,
      "uncovered_positions": [
        [
          4,
          4
        ],
        [
          8,
          8
        ],
        [
          5,
          5
        ],
        [
          7,
          7
        ],
        [
          0,
          0
        ],
        [
          1,
          1
        ],
        [
          3,
          3
        ],
        [
          2,
          2
        ],
        [
          6,
          6
        ]
      ]
    },
    "10": {
      "n": 10,
      "minimum_tiles": 18,
      "best_strategy": "diagonal_horizontal",
      "tiles": [
        [
          0,
          1,
          1,
          9
        ],
        [
          1,
          0,
          1,
          1
        ],
        [
          1,
          2,
          1,
          8
        ],
        [
          2,
          0,
          1,
          2
        ],
        [
          2,
          3,
          1,
          7
        ],
        [
          3,
          0,
          1,
          3
        ],
        [
          3,
          4,
          1,
          6
        ],
        [
          4,
          0,
          1,
          4
        ],
        [
          4,
          5,
          1,
          5
        ],
        [
          5,
          0,
          1,
          5
        ],
        [
          5,
          6,
          1,
          4
        ],
        [
          6,
          0,
          1,
          6
        ],
        [
          6,
          7,
          1,
          3
        ],
        [
          7,
          0,
          1,
          7
        ],
        [
          7,
          8,
          1,
          2
        ],
        [
          8,
          0,
          1,
          8
        ],
        [
          8,
          9,
          1,
          1
        ],
        [
          9,
          0,
          1,
          9
        ]
      ],
      "all_strategies": {
        "diagonal_horizontal": {
          "count": 18,
          "tiles": [
            [
              0,
              1,
              1,
              9
            ],
            [
              1,
              0,
              1,
              1
            ],
            [
              1,
              2,
              1,
              8
            ],
            [
              2,
              0,
              1,
              2
            ],
            [
              2,
              3,
              1,
              7
            ],
            [
              3,
              0,
              1,
              3
            ],
            [
              3,
              4,
              1,
              6
            ],
            [
              4,
              0,
              1,
              4
            ],
            [
              4,
              5,
              1,
              5
            ],
            [
              5,
              0,
              1,
              5
            ],
            [
              5,
              6,
              1,
              4
            ],
            [
              6,
              0,
              1,
              6
            ],
            [
              6,
              7,
              1,
              3
            ],
            [
              7,
              0,
              1,
              7
            ],
            [
              7,
              8,
              1,
              2
            ],
            [
              8,
              0,
              1,
              8
            ],
            [
              8,
              9,
              1,
              1
            ],
            [
              9,
              0,
              1,
              9
            ]
          ]
        },
        "anti_diagonal_horizontal": {
          "count": 18,
          "tiles": [
            [
              0,
              0,
              1,
              9
            ],
            [
              1,
              0,
              1,
              8
            ],
            [
              1,
              9,
              1,
              1
            ],
            [
              2,
              0,
              1,
              7
            ],
            [
              2,
              8,
              1,
              2
            ],
            [
              3,
              0,
              1,
              6
            ],
            [
              3,
              7,
              1,
              3
            ],
            [
              4,
              0,
              1,
              5
            ],
            [
              4,
              6,
              1,
              4
            ],
            [
              5,
              0,
              1,
              4
            ],
            [
              5,
              5,
              1,
              5
            ],
            [
              6,
              0,
              1,
              3
            ],
            [
              6,
              4,
              1,
              6
            ],
            [
              7,
              0,
              1,
              2
            ],
            [
              7,
              3,
              1,
              7
            ],
            [
              8,
              0,
              1,
              1
            ],
            [
              8,
              2,
              1,
              8
            ],
            [
              9,
              1,
              1,
              9
            ]
          ]
        },
        "optimized_vertical": {
          "count": 18,
          "tiles": [
            [
              1,
              0,
              9,
              1
            ],
            [
              0,
              1,
              1,
              1
            ],
            [
              2,
              1,
              8,
              1
            ],
            [
              0,
              2,
              2,
              1
            ],
            [
              3,
              2,
              7,
              1
            ],
            [
              0,
              3,
              3,
              1
            ],
            [
              4,
              3,
              6,
              1
            ],
            [
              0,
              4,
              4,
              1
            ],
            [
              5,
              4,
              5,
              1
            ],
            [
              0,
              5,
              5,
              1
            ],
            [
              6,
              5,
              4,
              1
            ],
            [
              0,
              6,
              6,
              1
            ],
            [
              7,
              6,
              3,
              1
            ],
            [
              0,
              7,
              7,
              1
            ],
            [
              8,
              7,
              2,
              1
            ],
            [
              0,
              8,
              8,
              1
            ],
            [
              9,
              8,
              1,
              1
            ],
            [
              0,
              9,
              9,
              1
            ]
          ]
        },
        "single_large_attempt": {
          "count": 18,
          "tiles": [
            [
              1,
              0,
              9,
              1
            ],
            [
              0,
              1,
              1,
              1
            ],
            [
              2,
              1,
              8,
              1
            ],
            [
              0,
              2,
              2,
              1
            ],
            [
              3,
              2,
              7,
              1
            ],
            [
              0,
              3,
              3,
              1
            ],
            [
              4,
              3,
              6,
              1
            ],
            [
              0,
              4,
              4,
              1
            ],
            [
              5,
              4,
              5,
              1
            ],
            [
              0,
              5,
              5,
              1
            ],
            [
              6,
              5,
              4,
              1
            ],
            [
              0,
              6,
              6,
              1
            ],
            [
              7,
              6,
              3,
              1
            ],
            [
              0,
              7,
              7,
              1
            ],
            [
              8,
              7,
              2,
              1
            ],
            [
              0,
              8,
              8,
              1
            ],
            [
              9,
              8,
              1,
              1
            ],
            [
              0,
              9,
              9,
              1
            ]
          ]
        }
      },
      "is_valid": true,
      "uncovered_positions": [
        [
          4,
          4
        ],
        [
          8,
          8
        ],
        [
          5,
          5
        ],
        [
          7,
          7
        ],
        [
          0,
          0
        ],
        [
          9,
          9
        ],
        [
          1,
          1
        ],
        [
          3,
          3
        ],
        [
          2,
          2
        ],
        [
          6,
          6
        ]
      ]
    }
  },
  "pattern_analysis": {
    "sizes": [
      2,
      3,
      4,
      5,
      6,
      7,
      8,
      9,
      10
    ],
    "minimum_tiles": [
      2,
      4,
      6,
      8,
      10,
      12,
      14,
      16,
      18
    ],
    "formula_check": [
      2,
      4,
      6,
      8,
      10,
      12,
      14,
      16,
      18
    ],
    "matches_2n_minus_2": true
  },
  "answer_for_2025": {
    "n": 2025,
    "minimum_tiles": 4048,
    "calculation": "2 \u00d7 2025 - 2 = 4048",
    "explanation": "Using diagonal strategy with vertical or horizontal tiles gives 2n-2 tiles"
  },
  "detailed_example_5x5": {
    "n": 5,
    "minimum_tiles": 8,
    "best_strategy": "diagonal_horizontal",
    "tiles": [
      [
        0,
        1,
        1,
        4
      ],
      [
        1,
        0,
        1,
        1
      ],
      [
        1,
        2,
        1,
        3
      ],
      [
        2,
        0,
        1,
        2
      ],
      [
        2,
        3,
        1,
        2
      ],
      [
        3,
        0,
        1,
        3
      ],
      [
        3,
        4,
        1,
        1
      ],
      [
        4,
        0,
        1,
        4
      ]
    ],
    "all_strategies": {
      "diagonal_horizontal": {
        "count": 8,
        "tiles": [
          [
            0,
            1,
            1,
            4
          ],
          [
            1,
            0,
            1,
            1
          ],
          [
            1,
            2,
            1,
            3
          ],
          [
            2,
            0,
            1,
            2
          ],
          [
            2,
            3,
            1,
            2
          ],
          [
            3,
            0,
            1,
            3
          ],
          [
            3,
            4,
            1,
            1
          ],
          [
            4,
            0,
            1,
            4
          ]
        ]
      },
      "anti_diagonal_horizontal": {
        "count": 8,
        "tiles": [
          [
            0,
            0,
            1,
            4
          ],
          [
            1,
            0,
            1,
            3
          ],
          [
            1,
            4,
            1,
            1
          ],
          [
            2,
            0,
            1,
            2
          ],
          [
            2,
            3,
            1,
            2
          ],
          [
            3,
            0,
            1,
            1
          ],
          [
            3,
            2,
            1,
            3
          ],
          [
            4,
            1,
            1,
            4
          ]
        ]
      },
      "optimized_vertical": {
        "count": 8,
        "tiles": [
          [
            1,
            0,
            4,
            1
          ],
          [
            0,
            1,
            1,
            1
          ],
          [
            2,
            1,
            3,
            1
          ],
          [
            0,
            2,
            2,
            1
          ],
          [
            3,
            2,
            2,
            1
          ],
          [
            0,
            3,
            3,
            1
          ],
          [
            4,
            3,
            1,
            1
          ],
          [
            0,
            4,
            4,
            1
          ]
        ]
      },
      "single_large_attempt": {
        "count": 8,
        "tiles": [
          [
            1,
            0,
            4,
            1
          ],
          [
            0,
            1,
            1,
            1
          ],
          [
            2,
            1,
            3,
            1
          ],
          [
            0,
            2,
            2,
            1
          ],
          [
            3,
            2,
            2,
            1
          ],
          [
            0,
            3,
            3,
            1
          ],
          [
            4,
            3,
            1,
            1
          ],
          [
            0,
            4,
            4,
            1
          ]
        ]
      }
    },
    "is_valid": true,
    "uncovered_positions": [
      [
        4,
        4
      ],
      [
        0,
        0
      ],
      [
        1,
        1
      ],
      [
        3,
        3
      ],
      [
        2,
        2
      ]
    ]
  },
  "metrics": {
    "runtime_ms": 24.24,
    "status": "success"
  }
}